[{"__symbolic":"module","version":3,"metadata":{"App":{"__symbolic":"class","decorators":[{"__symbolic":"call","expression":{"__symbolic":"reference","module":"@angular/core","name":"Injectable"}}],"members":{"__ctor__":[{"__symbolic":"constructor","parameterDecorators":[null,null,[{"__symbolic":"call","expression":{"__symbolic":"reference","module":"@angular/core","name":"Optional"}}]],"parameters":[{"__symbolic":"reference","module":"../../config/config","name":"Config"},{"__symbolic":"reference","module":"../../platform/platform","name":"Platform"},{"__symbolic":"reference","module":"./menu-controller","name":"MenuController"}]}],"setTitle":[{"__symbolic":"method"}],"setElementClass":[{"__symbolic":"method"}],"setEnabled":[{"__symbolic":"method"}],"_setDisableScroll":[{"__symbolic":"method"}],"isEnabled":[{"__symbolic":"method"}],"setScrolling":[{"__symbolic":"method"}],"isScrolling":[{"__symbolic":"method"}],"getActiveNav":[{"__symbolic":"method"}],"getActiveNavs":[{"__symbolic":"method"}],"getRootNav":[{"__symbolic":"method"}],"getRootNavs":[{"__symbolic":"method"}],"getRootNavById":[{"__symbolic":"method"}],"registerRootNav":[{"__symbolic":"method"}],"getActiveNavContainers":[{"__symbolic":"method"}],"present":[{"__symbolic":"method"}],"goBack":[{"__symbolic":"method"}],"navPop":[{"__symbolic":"method"}],"_enableInputBlurring":[{"__symbolic":"method"}],"getNavByIdOrName":[{"__symbolic":"method"}]}},"getNavByIdOrName":{"__symbolic":"function"},"findTopNavs":{"__symbolic":"function"}}},{"__symbolic":"module","version":1,"metadata":{"App":{"__symbolic":"class","decorators":[{"__symbolic":"call","expression":{"__symbolic":"reference","module":"@angular/core","name":"Injectable"}}],"members":{"__ctor__":[{"__symbolic":"constructor","parameterDecorators":[null,null,[{"__symbolic":"call","expression":{"__symbolic":"reference","module":"@angular/core","name":"Optional"}}]],"parameters":[{"__symbolic":"reference","module":"../../config/config","name":"Config"},{"__symbolic":"reference","module":"../../platform/platform","name":"Platform"},{"__symbolic":"reference","module":"./menu-controller","name":"MenuController"}]}],"setTitle":[{"__symbolic":"method"}],"setElementClass":[{"__symbolic":"method"}],"setEnabled":[{"__symbolic":"method"}],"_setDisableScroll":[{"__symbolic":"method"}],"isEnabled":[{"__symbolic":"method"}],"setScrolling":[{"__symbolic":"method"}],"isScrolling":[{"__symbolic":"method"}],"getActiveNav":[{"__symbolic":"method"}],"getActiveNavs":[{"__symbolic":"method"}],"getRootNav":[{"__symbolic":"method"}],"getRootNavs":[{"__symbolic":"method"}],"getRootNavById":[{"__symbolic":"method"}],"registerRootNav":[{"__symbolic":"method"}],"getActiveNavContainers":[{"__symbolic":"method"}],"present":[{"__symbolic":"method"}],"goBack":[{"__symbolic":"method"}],"navPop":[{"__symbolic":"method"}],"_enableInputBlurring":[{"__symbolic":"method"}],"getNavByIdOrName":[{"__symbolic":"method"}]}},"getNavByIdOrName":{"__symbolic":"function"},"findTopNavs":{"__symbolic":"function"}}}]